deep_brief/__init__.py
deep_brief/cli.py
deep_brief/analysis/__init__.py
deep_brief/analysis/api_image_captioner.py
deep_brief/analysis/default_rubrics.py
deep_brief/analysis/error_handling.py
deep_brief/analysis/frame_analyzer.py
deep_brief/analysis/image_captioner.py
deep_brief/analysis/object_detector.py
deep_brief/analysis/ocr_detector.py
deep_brief/analysis/rubric_system.py
deep_brief/analysis/speaker_diarization.py
deep_brief/analysis/speech_analyzer.py
deep_brief/analysis/transcriber.py
deep_brief/analysis/visual_analyzer.py
deep_brief/core/__init__.py
deep_brief/core/audio_extractor.py
deep_brief/core/exceptions.py
deep_brief/core/pipeline_coordinator.py
deep_brief/core/progress_tracker.py
deep_brief/core/scene_detector.py
deep_brief/core/video_processor.py
deep_brief/interface/__init__.py
deep_brief/interface/gradio_app.py
deep_brief/reports/__init__.py
deep_brief/reports/assessment_integration.py
deep_brief/reports/assessment_report.py
deep_brief/reports/assessment_session.py
deep_brief/reports/assessment_storage.py
deep_brief/reports/grading_sheet_renderer.py
deep_brief/reports/html_renderer.py
deep_brief/reports/report_generator.py
deep_brief/utils/__init__.py
deep_brief/utils/api_keys.py
deep_brief/utils/config.py
deep_brief/utils/progress_display.py
deep_brief-0.4.1.dist-info/METADATA
deep_brief-0.4.1.dist-info/WHEEL
deep_brief-0.4.1.dist-info/entry_points.txt
deep_brief-0.4.1.dist-info/RECORD
