Metadata-Version: 2.4
Name: deep-brief
Version: 0.4.1
Summary: A video analysis application for presentation feedback
Author-email: Michael Borck <michael@example.com>
Classifier: Development Status :: 3 - Alpha
Classifier: Intended Audience :: Education
Classifier: License :: OSI Approved :: MIT License
Classifier: Programming Language :: Python :: 3
Classifier: Programming Language :: Python :: 3.11
Classifier: Programming Language :: Python :: 3.12
Requires-Python: >=3.11
Requires-Dist: anthropic>=0.7.0
Requires-Dist: faster-whisper>=0.10.0
Requires-Dist: ffmpeg-python>=0.2.0
Requires-Dist: gradio>=4.8.0
Requires-Dist: jinja2>=3.1.0
Requires-Dist: numpy>=1.24.0
Requires-Dist: opencv-python>=4.8.0
Requires-Dist: pandas>=2.1.0
Requires-Dist: pillow>=10.1.0
Requires-Dist: pydantic-settings>=2.1.0
Requires-Dist: pydantic>=2.5.0
Requires-Dist: pytesseract>=0.3.10
Requires-Dist: python-dotenv>=1.0.0
Requires-Dist: pyyaml>=6.0.1
Requires-Dist: rich>=13.7.0
Requires-Dist: spacy>=3.7.0
Requires-Dist: torch>=2.2.0
Requires-Dist: torchvision>=0.17.0
Requires-Dist: tqdm>=4.66.0
Requires-Dist: transformers>=4.36.0
Requires-Dist: typer>=0.9.0
Requires-Dist: weasyprint>=60.0
Provides-Extra: api
Requires-Dist: google-generativeai>=0.3.0; extra == 'api'
Requires-Dist: openai>=1.12.0; extra == 'api'
Provides-Extra: build
Requires-Dist: build>=1.0.0; extra == 'build'
Requires-Dist: twine>=4.0.0; extra == 'build'
Provides-Extra: dev
Requires-Dist: basedpyright>=1.8.0; extra == 'dev'
Requires-Dist: pre-commit>=3.5.0; extra == 'dev'
Requires-Dist: pytest-asyncio>=0.21.0; extra == 'dev'
Requires-Dist: pytest-cov>=4.1.0; extra == 'dev'
Requires-Dist: pytest>=7.4.0; extra == 'dev'
Requires-Dist: ruff>=0.1.6; extra == 'dev'
Requires-Dist: types-pillow>=10.2.0; extra == 'dev'
Requires-Dist: types-pyyaml>=6.0.12; extra == 'dev'
Requires-Dist: types-requests>=2.31.0; extra == 'dev'
Requires-Dist: types-setuptools>=80.9.0; extra == 'dev'
Provides-Extra: gpu
Requires-Dist: torch>=2.2.0; extra == 'gpu'
Requires-Dist: torchvision>=0.17.0; extra == 'gpu'
